stravaio.py
swagger_client/__init__.py
swagger_client/api_client.py
swagger_client/configuration.py
swagger_client/rest.py
swagger_client/api/__init__.py
swagger_client/api/activities_api.py
swagger_client/api/athletes_api.py
swagger_client/api/clubs_api.py
swagger_client/api/gears_api.py
swagger_client/api/routes_api.py
swagger_client/api/running_races_api.py
swagger_client/api/segment_efforts_api.py
swagger_client/api/segments_api.py
swagger_client/api/streams_api.py
swagger_client/api/uploads_api.py
swagger_client/models/__init__.py
swagger_client/models/activity_stats.py
swagger_client/models/activity_total.py
swagger_client/models/activity_type.py
swagger_client/models/activity_zone.py
swagger_client/models/altitude_stream.py
swagger_client/models/base_stream.py
swagger_client/models/cadence_stream.py
swagger_client/models/comment.py
swagger_client/models/detailed_activity.py
swagger_client/models/detailed_athlete.py
swagger_client/models/detailed_club.py
swagger_client/models/detailed_gear.py
swagger_client/models/detailed_segment.py
swagger_client/models/detailed_segment_effort.py
swagger_client/models/distance_stream.py
swagger_client/models/error.py
swagger_client/models/explorer_response.py
swagger_client/models/explorer_segment.py
swagger_client/models/fault.py
swagger_client/models/heart_rate_zone_ranges.py
swagger_client/models/heartrate_stream.py
swagger_client/models/lap.py
swagger_client/models/lat_lng.py
swagger_client/models/lat_lng_stream.py
swagger_client/models/meta_activity.py
swagger_client/models/meta_athlete.py
swagger_client/models/meta_club.py
swagger_client/models/moving_stream.py
swagger_client/models/photos_summary.py
swagger_client/models/photos_summary_primary.py
swagger_client/models/polyline_map.py
swagger_client/models/power_stream.py
swagger_client/models/power_zone_ranges.py
swagger_client/models/route.py
swagger_client/models/route_direction.py
swagger_client/models/running_race.py
swagger_client/models/segment_leaderboard.py
stravaio-0.0.9.dist-info/LICENSE.txt
stravaio-0.0.9.dist-info/METADATA
stravaio-0.0.9.dist-info/WHEEL
stravaio-0.0.9.dist-info/top_level.txt
stravaio-0.0.9.dist-info/RECORD
