Metadata-Version: 2.1
Name: stravaio
Version: 0.0.9
Summary: Python client for Strava API with a focus on fluent data handling
Home-page: https://github.com/sladkovm/stravaio
Author: Maksym Sladkov
Author-email: sladkovm@gmail.com
License: MIT
Platform: UNKNOWN
Classifier: License :: OSI Approved :: MIT License
Classifier: Programming Language :: Python
Classifier: Programming Language :: Python :: 3.6
Classifier: Operating System :: OS Independent
Classifier: Development Status :: 3 - Alpha
Classifier: Intended Audience :: Developers
Classifier: Topic :: Scientific/Engineering
